prjitter
